telemetry/.env.example
telemetry/__init__.py
telemetry/constants.py
telemetry/types.py
telemetry/core/__init__.py
telemetry/services/__init__.py
telemetry/services/logging_service.py
telemetry/services/metrics_service.py
telemetry/services/tracing_service.py
telemetry/utils/error_util.py
telemetry/utils/logging_util.py
auto_genesis_telemetry_beta-0.0.3.dist-info/METADATA
auto_genesis_telemetry_beta-0.0.3.dist-info/WHEEL
auto_genesis_telemetry_beta-0.0.3.dist-info/RECORD
