Metadata-Version: 2.4
Name: auto-genesis-telemetry-beta
Version: 0.0.3
Summary: A unified OpenTelemetry-based SDK for metrics, logging, and tracing in Python applications.
Author-email: Muhamed Shahabas C <muhamed@autonomize.ai>
Requires-Python: >=3.12
Requires-Dist: opentelemetry-api>=1.20.0
Requires-Dist: opentelemetry-exporter-otlp-proto-grpc>=1.20.0
Requires-Dist: opentelemetry-instrumentation-fastapi>=0.41b0
Requires-Dist: opentelemetry-instrumentation-requests>=0.41b0
Requires-Dist: opentelemetry-instrumentation>=0.41b0
Requires-Dist: opentelemetry-sdk>=1.20.0
Provides-Extra: dev
Requires-Dist: black>=23.10.0; extra == 'dev'
Requires-Dist: commitizen>=3.12.0; extra == 'dev'
Requires-Dist: isort>=5.12.0; extra == 'dev'
Requires-Dist: mypy>=1.6.1; extra == 'dev'
Requires-Dist: pytest-cov>=4.1.0; extra == 'dev'
Requires-Dist: pytest>=7.4.3; extra == 'dev'
